LambdaRankNN/__init__.py
LambdaRankNN-0.1.1.dist-info/LICENSE
LambdaRankNN-0.1.1.dist-info/METADATA
LambdaRankNN-0.1.1.dist-info/WHEEL
LambdaRankNN-0.1.1.dist-info/top_level.txt
LambdaRankNN-0.1.1.dist-info/RECORD
