Metadata-Version: 2.1
Name: LambdaRankNN
Version: 0.1.1
Summary: LambdaRank Neural Netwrok model using Keras.
Home-page: https://github.com/liyinxiao/LambdaRankNN
Author: Yinxiao Li
Author-email: liyinxiao1227@gmail.com
License: UNKNOWN
Platform: UNKNOWN
Classifier: Programming Language :: Python :: 3
Classifier: License :: OSI Approved :: MIT License
Classifier: Operating System :: OS Independent
